docs/__init__.py
finmc/__init__.py
finmc/calc/__init__.py
finmc/calc/bond.py
finmc/calc/impliedvol.py
finmc/calc/option.py
finmc/models/__init__.py
finmc/models/base.py
finmc/models/heston.py
finmc/models/hullwhite.py
finmc/models/localvol.py
finmc/models/multi.py
finmc/plots/__init__.py
finmc/plots/asset.py
finmc/plots/dist.py
finmc/plots/impliedvol.py
finmc/utils/__init__.py
finmc/utils/assets.py
finmc/utils/bs.py
finmc/utils/interp.py
finmc/utils/mc.py
tests/heston/__init__.py
tests/heston/dataset.py
tests/heston/helpers.py
tests/hullwhite/__init__.py
tests/hullwhite/dataset.py
tests/localvol/__init__.py
tests/localvol/dataset.py
tests/multi/__init__.py
tests/multi/dataset.py
finmc-0.0.8.dist-info/LICENSE
finmc-0.0.8.dist-info/METADATA
finmc-0.0.8.dist-info/WHEEL
finmc-0.0.8.dist-info/top_level.txt
finmc-0.0.8.dist-info/RECORD
