Metadata-Version: 2.1
Name: finmc
Version: 0.0.8
Summary: finmc is a Python library for Monte Carlo Simulation.
Home-page: https://github.com/finlib/finmc/
Author: somdipdatta
License-File: LICENSE
Requires-Dist: pandas
Requires-Dist: numpy
Requires-Dist: scipy
Requires-Dist: matplotlib
Provides-Extra: test
Requires-Dist: pytest; extra == "test"
Requires-Dist: coverage; extra == "test"
Requires-Dist: flake8; extra == "test"
Requires-Dist: isort; extra == "test"
Requires-Dist: pytest-cov; extra == "test"
Requires-Dist: mypy; extra == "test"
Requires-Dist: gitchangelog; extra == "test"
Requires-Dist: mkdocs; extra == "test"
Requires-Dist: mkdocstrings; extra == "test"
Requires-Dist: mkdocstrings-python; extra == "test"
Requires-Dist: mkdocs-material; extra == "test"
Requires-Dist: line-profiler; extra == "test"
Requires-Dist: matplotlib; extra == "test"
Requires-Dist: nbformat; extra == "test"
Requires-Dist: nbmake; extra == "test"
Requires-Dist: nb-clean; extra == "test"
Requires-Dist: pandas; extra == "test"
Requires-Dist: numpy; extra == "test"
Requires-Dist: scipy; extra == "test"
Requires-Dist: ruff; extra == "test"
